konsoru/__init__.py
konsoru/config.py
konsoru/core.py
konsoru/decorators.py
konsoru/exceptions.py
konsoru/utils.py
konsoru-0.1.2.dist-info/LICENSE
konsoru-0.1.2.dist-info/METADATA
konsoru-0.1.2.dist-info/WHEEL
konsoru-0.1.2.dist-info/top_level.txt
konsoru-0.1.2.dist-info/RECORD
