Metadata-Version: 2.1
Name: konsoru
Version: 0.1.2
Summary: A functional programming styled CLI console application framework based on argparse
Home-page: https://github.com/DonovanWu/konsoru
Author: Wenrui Wu
License: UNKNOWN
Platform: UNKNOWN
Requires-Python: >=3.5
